bat_function_call_define.py
bat_menu_auto.py
batframe_main.py
nuitka_dependency_files.py
batframes-1.0.0.7.data/data/bat_inner_module/inner_demo.py
batframes-1.0.0.7.data/data/bat_inner_module/inner_demo1.py
batframes-1.0.0.7.data/data/bat_inner_module/readme_for_inner.md
batframes-1.0.0.7.data/data/config/batframe/bat_tools_config.json
batframes-1.0.0.7.data/data/config/img/Excel.png
batframes-1.0.0.7.data/data/config/img/excel.gif
batframes-1.0.0.7.data/data/config/img/little_bear.png
batframes-1.0.0.7.data/data/config/img/table_arrow9_transparent_64.ico
batframes-1.0.0.7.dist-info/METADATA
batframes-1.0.0.7.dist-info/WHEEL
batframes-1.0.0.7.dist-info/entry_points.txt
batframes-1.0.0.7.dist-info/top_level.txt
batframes-1.0.0.7.dist-info/RECORD
